weblib/__init__.py
weblib/app.py
weblib/auth.py
weblib/assets/__init__.py
weblib/assets/static.py
weblib/cli/__init__.py
weblib/cli/main.py
weblib/css/__init__.py
weblib/css/css.py
weblib/elements/__init__.py
weblib/elements/core.py
weblib/orm/__init__.py
weblib/orm/fields.py
weblib/orm/mysql_impl.py
weblib/orm/postgres_impl.py
weblib/orm/protocol.py
weblib/orm/sqlite_impl.py
weblib/page/__init__.py
weblib/page/page.py
weblib/routing/__init__.py
weblib/routing/core.py
weblib/routing/responses.py
weblib/runtime/__init__.py
weblib/runtime/adapters.py
weblib/runtime/asgi.py
weblib/runtime/middleware.py
weblib/utils/__init__.py
weblib/utils/escaping.py
weblib_py-0.1.13.dist-info/METADATA
weblib_py-0.1.13.dist-info/WHEEL
weblib_py-0.1.13.dist-info/entry_points.txt
weblib_py-0.1.13.dist-info/top_level.txt
weblib_py-0.1.13.dist-info/RECORD
