Metadata-Version: 2.4
Name: weblib-py
Version: 0.1.13
Summary: WebLib v2 – Minimal ASGI web library MVP per specifiche
Author: WebLib Authors
License: MIT
Project-URL: Homepage, https://example.local/weblib
Classifier: Programming Language :: Python :: 3
Classifier: Programming Language :: Python :: 3.11
Classifier: License :: OSI Approved :: MIT License
Classifier: Framework :: AsyncIO
Requires-Python: >=3.11
